LICENSE
MANIFEST.in
README.md
requirements.txt
setup.cfg
setup.py
calcalc/CalCalc.py
calcalc/__init__.py
calcalc/helper.py
calcalc/tester2/__init__.py
calcalc/tester2/test2.py
calcalc_toy.egg-info/PKG-INFO
calcalc_toy.egg-info/SOURCES.txt
calcalc_toy.egg-info/dependency_links.txt
calcalc_toy.egg-info/top_level.txt
dist/calcalc-toy-1.7.tar.gz
tester1/__init__.py
tester1/test1.py