Metadata-Version: 2.1
Name: calcalc-toy
Version: 1.8
Summary: A calculator that evaluates string expressions both locally or using WolframAlpha.
Author: Yang Lyu
Author-email: yanglyu902@gmail.com
License: MIT License
Platform: UNKNOWN
Requires-Python: >=3
License-File: LICENSE
